spanns/__init__.py
spanns/spanns.py
spanns-1.1.1.dist-info/LICENSE
spanns-1.1.1.dist-info/METADATA
spanns-1.1.1.dist-info/WHEEL
spanns-1.1.1.dist-info/top_level.txt
spanns-1.1.1.dist-info/RECORD
