Metadata-Version: 2.2
Name: spanns
Version: 1.1.1
Summary: The Survival Probability Adapted Nuclear Norm Shrinkage Denoiser
Author: Gabriella Chaos
Project-URL: Homepage, https://github.com/Gabriella-Chaos/spanns
Classifier: Programming Language :: Python :: 3
Classifier: License :: OSI Approved :: MIT License
Classifier: Operating System :: OS Independent
Requires-Python: >=3.8
License-File: LICENSE
Requires-Dist: vapoursynth
Requires-Dist: numpy
Requires-Dist: pywavelets
Requires-Dist: scipy
